dibisoplot/HAL_doc_types_names.toml
dibisoplot/__init__.py
dibisoplot/_version.py
dibisoplot/dibisoplot.py
dibisoplot/translation.py
dibisoplot/utils.py
dibisoplot/biso/__init__.py
dibisoplot/biso/biso.py
dibisoplot/locales/dibisoplot.pot
dibisoplot/locales/fr/LC_MESSAGES/dibisoplot.mo
dibisoplot/locales/fr/LC_MESSAGES/dibisoplot.po
dibisoplot/pubpart/__init__.py
dibisoplot/pubpart/pubpart.py
dibisoplot-0.8.dist-info/licenses/LICENSE.txt
dibisoplot-0.8.dist-info/METADATA
dibisoplot-0.8.dist-info/WHEEL
dibisoplot-0.8.dist-info/top_level.txt
dibisoplot-0.8.dist-info/RECORD
