Metadata-Version: 2.4
Name: dibisoplot
Version: 0.8
Summary: A Python library for plotting bibliometric research data, developed at the DiBISO.
Author-email: Romain Thomas <contact@romainthomas.net>
License-Expression: GPL-3.0-only
Project-URL: Homepage, https://pypi.org/project/dibisoplot/
Project-URL: Repository, https://github.com/dibiso-upsaclay/dibisoplot
Project-URL: Documentation, https://dibiso-upsaclay.github.io/dibisoplot/
Keywords: DiBISO,Data analysis,Scientific research,Plotly
Classifier: Development Status :: 4 - Beta
Classifier: Intended Audience :: Science/Research
Classifier: Programming Language :: Python
Classifier: Programming Language :: Python :: 3
Classifier: Topic :: Scientific/Engineering :: Visualization
Classifier: Typing :: Typed
Requires-Python: >=3.10
License-File: LICENSE.txt
Requires-Dist: numpy>=1.21.5
Requires-Dist: pandas>=2.0.1
Requires-Dist: plotly>=5.15.0
Requires-Dist: kaleido
Requires-Dist: tqdm>=4.65.0
Requires-Dist: requests
Requires-Dist: emoji-country-flag
Requires-Dist: openalex-analysis>=0.15
Requires-Dist: elasticsearch<9,>7
Requires-Dist: pylatexenc
Requires-Dist: pyalex
Dynamic: license-file
